pkg_upload/__init__.py
pkg_upload/setup.py
pkg_upload-0.0.1.dist-info/METADATA
pkg_upload-0.0.1.dist-info/WHEEL
pkg_upload-0.0.1.dist-info/top_level.txt
pkg_upload-0.0.1.dist-info/RECORD
