Metadata-Version: 2.1
Name: pkg-upload
Version: 0.0.1
Summary: A package for uploading packages. Made with setuptools
Home-page: https://github.com
Author: DiscordDev
Author-email: example@example.com
License: UNKNOWN
Platform: UNKNOWN
Classifier: Programming Language :: Python :: 3
Classifier: License :: OSI Approved :: MIT License
Classifier: Operating System :: OS Independent
Requires-Python: >=3.6
